{
"meta":{"test_sets":[],"test_metrics":[],"learn_metrics":[{"best_value":"Min","name":"Logloss"}],"launch_mode":"Train","parameters":"","iteration_count":100,"learn_sets":["learn"],"name":"experiment"},
"iterations":[
{"learn":[0.6610955271],"iteration":0,"passed_time":0.05832838942,"remaining_time":5.774510552},
{"learn":[0.6145708909],"iteration":1,"passed_time":0.05891028903,"remaining_time":2.886604163},
{"learn":[0.5673725093],"iteration":2,"passed_time":0.05914106334,"remaining_time":1.912227715},
{"learn":[0.5303975329],"iteration":3,"passed_time":0.05945801341,"remaining_time":1.426992322},
{"learn":[0.5042370698],"iteration":4,"passed_time":0.05989974053,"remaining_time":1.13809507},
{"learn":[0.4793317988],"iteration":5,"passed_time":0.06044377037,"remaining_time":0.9469524025},
{"learn":[0.4557885389],"iteration":6,"passed_time":0.06102701261,"remaining_time":0.8107874533},
{"learn":[0.4376101708],"iteration":7,"passed_time":0.06158524111,"remaining_time":0.7082302728},
{"learn":[0.4171111959],"iteration":8,"passed_time":0.06209907575,"remaining_time":0.6278906548},
{"learn":[0.3979571774],"iteration":9,"passed_time":0.06286003309,"remaining_time":0.5657402978},
{"learn":[0.3815161637],"iteration":10,"passed_time":0.06346973819,"remaining_time":0.5135278817},
{"learn":[0.3618061581],"iteration":11,"passed_time":0.06406037645,"remaining_time":0.469776094},
{"learn":[0.3499256988],"iteration":12,"passed_time":0.06468782582,"remaining_time":0.4329108343},
{"learn":[0.33853688],"iteration":13,"passed_time":0.06528600285,"remaining_time":0.4010425889},
{"learn":[0.3235440548],"iteration":14,"passed_time":0.06576195305,"remaining_time":0.3726510673},
{"learn":[0.3105055049],"iteration":15,"passed_time":0.06627302527,"remaining_time":0.3479333827},
{"learn":[0.3004489548],"iteration":16,"passed_time":0.06694311845,"remaining_time":0.3268399313},
{"learn":[0.2920526766],"iteration":17,"passed_time":0.06744461791,"remaining_time":0.3072477038},
{"learn":[0.2839634653],"iteration":18,"passed_time":0.06809127378,"remaining_time":0.2902838514},
{"learn":[0.2753781402],"iteration":19,"passed_time":0.06866878362,"remaining_time":0.2746751345},
{"learn":[0.2658197756],"iteration":20,"passed_time":0.0693330549,"remaining_time":0.2608243494},
{"learn":[0.2576605],"iteration":21,"passed_time":0.06979389824,"remaining_time":0.2474510938},
{"learn":[0.248926202],"iteration":22,"passed_time":0.07045343946,"remaining_time":0.2358658625},
{"learn":[0.2412104562],"iteration":23,"passed_time":0.07102759274,"remaining_time":0.2249207103},
{"learn":[0.2322909615],"iteration":24,"passed_time":0.07163470132,"remaining_time":0.214904104},
{"learn":[0.2255036303],"iteration":25,"passed_time":0.07218692658,"remaining_time":0.2054550987},
{"learn":[0.2181932435],"iteration":26,"passed_time":0.07272405502,"remaining_time":0.1966242969},
{"learn":[0.2106488572],"iteration":27,"passed_time":0.07328519871,"remaining_time":0.1884476538},
{"learn":[0.2043438849],"iteration":28,"passed_time":0.07394540353,"remaining_time":0.1810387466},
{"learn":[0.1990736785],"iteration":29,"passed_time":0.07444828342,"remaining_time":0.1737126613},
{"learn":[0.1948116909],"iteration":30,"passed_time":0.07495299283,"remaining_time":0.166830855},
{"learn":[0.1872116237],"iteration":31,"passed_time":0.07549291299,"remaining_time":0.1604224401},
{"learn":[0.183055689],"iteration":32,"passed_time":0.07604796472,"remaining_time":0.1544004132},
{"learn":[0.1781905195],"iteration":33,"passed_time":0.07657853357,"remaining_time":0.1486524475},
{"learn":[0.1752233632],"iteration":34,"passed_time":0.07706984758,"remaining_time":0.1431297169},
{"learn":[0.1703783595],"iteration":35,"passed_time":0.07773111647,"remaining_time":0.1381886515},
{"learn":[0.1669355611],"iteration":36,"passed_time":0.07824179594,"remaining_time":0.1332225174},
{"learn":[0.1635430235],"iteration":37,"passed_time":0.07871110785,"remaining_time":0.1284233865},
{"learn":[0.1593781838],"iteration":38,"passed_time":0.07938338088,"remaining_time":0.1241637496},
{"learn":[0.1559104494],"iteration":39,"passed_time":0.08016017349,"remaining_time":0.1202402602},
{"learn":[0.1529549695],"iteration":40,"passed_time":0.08065223675,"remaining_time":0.1160605358},
{"learn":[0.1485995866],"iteration":41,"passed_time":0.08140942548,"remaining_time":0.11242254},
{"learn":[0.1457898987],"iteration":42,"passed_time":0.08190532217,"remaining_time":0.1085721713},
{"learn":[0.1429485524],"iteration":43,"passed_time":0.08261427744,"remaining_time":0.105145444},
{"learn":[0.1399013135],"iteration":44,"passed_time":0.08307743874,"remaining_time":0.1015390918},
{"learn":[0.1367171801],"iteration":45,"passed_time":0.08361149534,"remaining_time":0.09815262496},
{"learn":[0.1345289248],"iteration":46,"passed_time":0.08414078252,"remaining_time":0.09488215902},
{"learn":[0.1320021467],"iteration":47,"passed_time":0.0846851241,"remaining_time":0.09174221777},
{"learn":[0.1291168872],"iteration":48,"passed_time":0.08522015757,"remaining_time":0.08869853135},
{"learn":[0.1265473868],"iteration":49,"passed_time":0.08580923947,"remaining_time":0.08580923947},
{"learn":[0.1231325332],"iteration":50,"passed_time":0.08630830444,"remaining_time":0.08292366505},
{"learn":[0.1193966406],"iteration":51,"passed_time":0.08691800028,"remaining_time":0.08023200026},
{"learn":[0.1170674198],"iteration":52,"passed_time":0.08748947757,"remaining_time":0.07758500841},
{"learn":[0.1140218601],"iteration":53,"passed_time":0.0880387614,"remaining_time":0.07499598193},
{"learn":[0.1117198833],"iteration":54,"passed_time":0.08845667542,"remaining_time":0.07237364352},
{"learn":[0.1075818066],"iteration":55,"passed_time":0.08902867664,"remaining_time":0.06995110307},
{"learn":[0.1046072501],"iteration":56,"passed_time":0.08957143021,"remaining_time":0.06757142981},
{"learn":[0.1015980589],"iteration":57,"passed_time":0.09000934782,"remaining_time":0.06517918291},
{"learn":[0.09962092191],"iteration":58,"passed_time":0.0906058975,"remaining_time":0.06296342029},
{"learn":[0.09740945274],"iteration":59,"passed_time":0.09127778008,"remaining_time":0.06085185339},
{"learn":[0.09494859725],"iteration":60,"passed_time":0.09183686739,"remaining_time":0.05871537424},
{"learn":[0.09387881703],"iteration":61,"passed_time":0.09246013456,"remaining_time":0.05666911473},
{"learn":[0.09230773231],"iteration":62,"passed_time":0.09299190329,"remaining_time":0.05461429241},
{"learn":[0.09014781556],"iteration":63,"passed_time":0.09366632451,"remaining_time":0.05268730754},
{"learn":[0.08902155552],"iteration":64,"passed_time":0.09423508877,"remaining_time":0.05074197088},
{"learn":[0.08687494301],"iteration":65,"passed_time":0.09478332705,"remaining_time":0.04882777454},
{"learn":[0.0847924599],"iteration":66,"passed_time":0.09550717698,"remaining_time":0.04704084836},
{"learn":[0.08282000902],"iteration":67,"passed_time":0.09603866175,"remaining_time":0.04519466435},
{"learn":[0.08168216835],"iteration":68,"passed_time":0.09661206347,"remaining_time":0.04340541982},
{"learn":[0.07938655256],"iteration":69,"passed_time":0.09716100393,"remaining_time":0.04164043025},
{"learn":[0.07759060976],"iteration":70,"passed_time":0.09762252321,"remaining_time":0.03987398835},
{"learn":[0.07626108044],"iteration":71,"passed_time":0.09817574309,"remaining_time":0.03817945565},
{"learn":[0.07456405529],"iteration":72,"passed_time":0.09870455496,"remaining_time":0.03650716416},
{"learn":[0.07290017903],"iteration":73,"passed_time":0.09927939807,"remaining_time":0.03488195067},
{"learn":[0.07167434853],"iteration":74,"passed_time":0.09982650823,"remaining_time":0.03327550274},
{"learn":[0.06997931028],"iteration":75,"passed_time":0.1003314615,"remaining_time":0.03168361941},
{"learn":[0.06825348038],"iteration":76,"passed_time":0.1008419835,"remaining_time":0.03012163144},
{"learn":[0.06661372922],"iteration":77,"passed_time":0.1013999682,"remaining_time":0.02859999103},
{"learn":[0.06505242747],"iteration":78,"passed_time":0.101980526,"remaining_time":0.02710874741},
{"learn":[0.06356522381],"iteration":79,"passed_time":0.1025724752,"remaining_time":0.0256431188},
{"learn":[0.06274648981],"iteration":80,"passed_time":0.1030001649,"remaining_time":0.02416053252},
{"learn":[0.06136259408],"iteration":81,"passed_time":0.1034192758,"remaining_time":0.02270179224},
{"learn":[0.0600407399],"iteration":82,"passed_time":0.103771114,"remaining_time":0.02125432456},
{"learn":[0.05877818103],"iteration":83,"passed_time":0.1042180705,"remaining_time":0.01985106104},
{"learn":[0.05791957765],"iteration":84,"passed_time":0.1044958683,"remaining_time":0.01844044735},
{"learn":[0.05711617212],"iteration":85,"passed_time":0.1048756888,"remaining_time":0.01707278655},
{"learn":[0.05633881418],"iteration":86,"passed_time":0.1052535247,"remaining_time":0.01572753817},
{"learn":[0.0555997621],"iteration":87,"passed_time":0.1058648332,"remaining_time":0.01443611362},
{"learn":[0.05489894901],"iteration":88,"passed_time":0.1061264709,"remaining_time":0.01311675483},
{"learn":[0.0542317943],"iteration":89,"passed_time":0.1063552591,"remaining_time":0.01181725101},
{"learn":[0.05399984633],"iteration":90,"passed_time":0.1068140399,"remaining_time":0.01056402592},
{"learn":[0.05357772233],"iteration":91,"passed_time":0.1072327741,"remaining_time":0.009324589053},
{"learn":[0.05335398872],"iteration":92,"passed_time":0.1076718237,"remaining_time":0.008104330816},
{"learn":[0.0531503184],"iteration":93,"passed_time":0.1081254385,"remaining_time":0.006901623732},
{"learn":[0.05295290582],"iteration":94,"passed_time":0.1084408044,"remaining_time":0.005707410757},
{"learn":[0.0527703608],"iteration":95,"passed_time":0.1088757142,"remaining_time":0.004536488092},
{"learn":[0.0525901525],"iteration":96,"passed_time":0.1092255779,"remaining_time":0.003378110657},
{"learn":[0.05242758204],"iteration":97,"passed_time":0.1095916234,"remaining_time":0.002236563742},
{"learn":[0.05226978482],"iteration":98,"passed_time":0.1099010015,"remaining_time":0.001110111126},
{"learn":[0.05212178548],"iteration":99,"passed_time":0.1102555621,"remaining_time":0}
]}":0}
]}maining_time":0}
]}}}